baqup_agent/__init__.py
baqup_agent/config.py
baqup_agent/py.typed
baqup_agent-0.0.1.dist-info/METADATA
baqup_agent-0.0.1.dist-info/WHEEL
baqup_agent-0.0.1.dist-info/licenses/LICENSE
baqup_agent-0.0.1.dist-info/RECORD
